graphs_Dennis/__init__.py
graphs_Dennis/heapq.py
graphs_Dennis/sp.py
graphs_dennis-0.0.4.dist-info/METADATA
graphs_dennis-0.0.4.dist-info/WHEEL
graphs_dennis-0.0.4.dist-info/RECORD
